assistant/__init__.py
assistant/chatbot.py
assistant/core.py
chatgpt_commit_assistant/__init__.py
chatgpt_commit_assistant/chatbot.py
chatgpt_commit_assistant/commit_assistant.py
tests/__init__.py
tests/context.py
tests/test_assistant.py
tests/test_chatbot.py
tests/test_commit_assistant.py
git_lazy_commit-0.14.0.dist-info/LICENSE
git_lazy_commit-0.14.0.dist-info/METADATA
git_lazy_commit-0.14.0.dist-info/WHEEL
git_lazy_commit-0.14.0.dist-info/entry_points.txt
git_lazy_commit-0.14.0.dist-info/top_level.txt
git_lazy_commit-0.14.0.dist-info/RECORD
