Metadata-Version: 2.1
Name: git-lazy-commit
Version: 0.14.0
License-File: LICENSE
Requires-Dist: openai
Requires-Dist: GitPython
